epilepsy_bids_loader/__init__.py
epilepsy_bids_loader/bids_loader.py
epilepsy_bids_loader/common.py
epilepsy_bids_loader/cross_validation.py
epilepsy_bids_loader/manifest_loader.py
epilepsy_bids_loader/montage.py
epilepsy_bids_loader/segment.py
epilepsy_bids_loader/structs.py
epilepsy_bids_loader/utils.py
epilepsy_bids_loader-0.7.0.dist-info/LICENSE
epilepsy_bids_loader-0.7.0.dist-info/METADATA
epilepsy_bids_loader-0.7.0.dist-info/WHEEL
epilepsy_bids_loader-0.7.0.dist-info/top_level.txt
epilepsy_bids_loader-0.7.0.dist-info/RECORD
