Metadata-Version: 2.2
Name: epilepsy-bids-loader
Version: 0.7.0
Summary: A data loader for BIDS compatible epilepsy EEG datasets for machine learning pipelines.
Author-email: Johnson Zhou <johnson.j.zhou@icloud.com>
Requires-Python: >=3.11
License-File: LICENSE
Requires-Dist: numpy
Requires-Dist: scipy
Requires-Dist: torch
Requires-Dist: matplotlib
Requires-Dist: pandas
Requires-Dist: pyEDFlib
Requires-Dist: pyyaml
